spousefriendly-0.1.0.dist-info/RECORD
spousefriendly-0.1.0.dist-info/DESCRIPTION.rst
spousefriendly-0.1.0.dist-info/METADATA
spousefriendly-0.1.0.dist-info/top_level.txt
spousefriendly-0.1.0.dist-info/metadata.json
spousefriendly-0.1.0.dist-info/WHEEL
spousefriendly/spousefriendly.py
spousefriendly/__init__.py
