Metadata-Version: 2.0
Name: spousefriendly
Version: 0.1.0
Summary: Be nice to your spouse - give your command line scripts some GUI feedback when needed.
Home-page: https://bitbucket.com/spookylukey/spousefriendly
Author: Luke Plant
Author-email: L.Plant.98@cantab.net
License: ISCL
Keywords: spousefriendly
Platform: UNKNOWN
Classifier: Development Status :: 2 - Pre-Alpha
Classifier: Intended Audience :: Developers
Classifier: License :: OSI Approved :: ISC License (ISCL)
Classifier: Natural Language :: English
Classifier: Programming Language :: Python :: 2
Classifier: Programming Language :: Python :: 2.7
Classifier: Programming Language :: Python :: 3
Classifier: Programming Language :: Python :: 3.4
Requires-Dist: easygui (>=0.97.4)
